{
  "$schema": "vscode://schemas/color-theme",
  "name": "XELA OLED Perfect — True Black",
  "type": "dark",
  "semanticHighlighting": true,
  "xGenerated": true,
  "colors": {
    "titleBar.activeBackground": "#000000",
    "titleBar.inactiveBackground": "#000000",
    "titleBar.activeForeground": "#E0E0E0",
    "titleBar.inactiveForeground": "#707070",
    "titleBar.border": "#1F1F1F",
    "window.activeBorder": "#00E5FF",
    "window.inactiveBorder": "#1F1F1F",
    "activityBar.background": "#000000",
    "activityBar.foreground": "#E0E0E0",
    "activityBar.inactiveForeground": "#707070",
    "activityBar.border": "#1F1F1F",
    "activityBar.activeBorder": "#00E5FF",
    "activityBarBadge.background": "#00E5FF",
    "activityBarBadge.foreground": "#000000",
    "sideBar.background": "#000000",
    "sideBar.foreground": "#E0E0E0",
    "sideBar.border": "#1F1F1F",
    "sideBarTitle.foreground": "#B0B0B0",
    "sideBarSectionHeader.background": "#0A0A0A",
    "sideBarSectionHeader.foreground": "#E0E0E0",
    "sideBar.dropBackground": "#00E5FF21",
    "statusBar.background": "#000000",
    "statusBar.foreground": "#E0E0E0",
    "statusBar.border": "#1F1F1F",
    "statusBar.noFolderBackground": "#0A0A0A",
    "statusBar.noFolderForeground": "#B0B0B0",
    "statusBar.debuggingBackground": "#FFB300",
    "statusBar.debuggingForeground": "#000000",
    "statusBarItem.hoverBackground": "#0A0A0A",
    "statusBarItem.remoteBackground": "#00E5FF",
    "statusBarItem.remoteForeground": "#000000",
    "statusBarItem.prominentBackground": "#0A0A0A",
    "statusBarItem.prominentHoverBackground": "#141414",
    "statusBarItem.errorBackground": "#FF5252",
    "statusBarItem.errorForeground": "#000000",
    "statusBarItem.warningBackground": "#FFB300",
    "statusBarItem.warningForeground": "#000000",
    "panel.background": "#000000",
    "panel.border": "#1F1F1F",
    "panel.dropBorder": "#00E5FF",
    "panelTitle.activeForeground": "#E0E0E0",
    "panelTitle.activeBorder": "#00E5FF",
    "panelTitle.inactiveForeground": "#B0B0B0",
    "editorGroupHeader.tabsBackground": "#0A0A0A",
    "editorGroupHeader.tabsBorder": "#1F1F1F",
    "editorGroup.border": "#1F1F1F",
    "editorGroup.dropBackground": "#00E5FF21",
    "tab.activeBackground": "#000000",
    "tab.inactiveBackground": "#000000",
    "tab.border": "#0A0A0A",
    "tab.activeForeground": "#E0E0E0",
    "tab.inactiveForeground": "#FFFFFF",
    "tab.activeBorderTop": "#00E5FF",
    "tab.unfocusedActiveBorderTop": "#FFB30087",
    "tab.hoverBackground": "#141414",
    "tab.hoverForeground": "#E0E0E0",
    "tab.unfocusedHoverBackground": "#141414",
    "tab.activeModifiedBorder": "#FFB300",
    "tab.hoverBorder": "#141414",
    "tab.lastPinnedBorder": "#1F1F1F",
    "editor.background": "#000000",
    "editor.foreground": "#E0E0E0",
    "editor.lineHighlightBackground": "#0A0A0A80",
    "editor.selectionBackground": "#00E5FF33",
    "editor.inactiveSelectionBackground": "#00E5FF99",
    "editor.selectionHighlightBackground": "#00E5FF99",
    "editor.selectionHighlightBorder": "#00E5FF54",
    "editor.wordHighlightBackground": "#00E5FF1A",
    "editor.wordHighlightStrongBackground": "#00E5FF2B",
    "editor.foldBackground": "#00000080",
    "editor.findMatchBackground": "#00000000",
    "editor.findMatchBorder": "#FFB300",
    "editor.findMatchHighlightBackground": "#0A0A0A80",
    "editor.findMatchHighlightBorder": "#FFB30087",
    "editor.hoverHighlightBackground": "#0A0A0A80",
    "editorCursor.foreground": "#00E5FF",
    "editorLineNumber.foreground": "#2F2F2F",
    "editorLineNumber.activeForeground": "#FFFFFF",
    "editorHoverWidget.background": "#141414",
    "editorHoverWidget.border": "#1F1F1F",
    "editorWidget.background": "#141414",
    "editorWidget.foreground": "#E0E0E0",
    "editorWidget.border": "#1F1F1F",
    "editorWidget.resizeBorder": "#00E5FF",
    "editorIndentGuide.background1": "#0A0A0A",
    "editorIndentGuide.activeBackground1": "#707070B3",
    "editorBracketMatch.background": "#0A0A0A",
    "editorBracketMatch.border": "#FFB30087",
    "editorBracketHighlight.foreground1": "#00E5FF",
    "editorBracketHighlight.foreground2": "#FFB300",
    "editorBracketHighlight.foreground3": "#FF5252",
    "editorBracketHighlight.foreground4": "#00E5FF",
    "editorBracketHighlight.foreground5": "#00E676",
    "editorBracketHighlight.foreground6": "#40EAFF",
    "editorBracketPairGuide.activeBackground1": "#00E5FF54",
    "editorBracketPairGuide.activeBackground2": "#FFB30054",
    "editorBracketPairGuide.activeBackground3": "#FF525254",
    "editorBracketPairGuide.activeBackground4": "#00E5FF54",
    "editorBracketPairGuide.activeBackground5": "#00E67654",
    "editorBracketPairGuide.activeBackground6": "#40EAFF54",
    "diffEditor.insertedTextBackground": "#00E67621",
    "diffEditor.removedTextBackground": "#FF525221",
    "diffEditor.insertedLineBackground": "#00E6761A",
    "diffEditor.removedLineBackground": "#FF52521A",
    "editorOverviewRuler.errorForeground": "#FF5252AB",
    "editorOverviewRuler.warningForeground": "#FFB300AB",
    "editorOverviewRuler.infoForeground": "#00E5FF87",
    "editorOverviewRuler.findMatchForeground": "#FFB30087",
    "editorOverviewRuler.modifiedForeground": "#FFB30066",
    "editorOverviewRuler.addedForeground": "#00E67666",
    "editorOverviewRuler.deletedForeground": "#FF525266",
    "editorGutter.addedBackground": "#00E676AB",
    "editorGutter.modifiedBackground": "#FFB300AB",
    "editorGutter.deletedBackground": "#FF5252AB",
    "editorGutter.commentRangeForeground": "#707070",
    "minimap.findMatchHighlight": "#FFB30099",
    "minimap.selectionHighlight": "#00E5FF54",
    "minimap.selectionOccurrenceHighlight": "#00E5FF33",
    "minimap.errorHighlight": "#FF525299",
    "minimap.warningHighlight": "#FFB30099",
    "list.activeSelectionBackground": "#0A0A0A",
    "list.activeSelectionForeground": "#E0E0E0",
    "list.inactiveSelectionBackground": "#000000",
    "list.inactiveSelectionForeground": "#E0E0E0",
    "list.hoverBackground": "#0A0A0A",
    "list.focusBackground": "#000000",
    "list.focusForeground": "#E0E0E0",
    "list.highlightForeground": "#00E5FF",
    "list.warningForeground": "#FFB300",
    "list.errorForeground": "#FF5252",
    "list.dropBackground": "#00E5FF21",
    "input.background": "#0A0A0A",
    "input.foreground": "#E0E0E0",
    "input.border": "#1F1F1F",
    "input.placeholderForeground": "#707070",
    "inputOption.activeBorder": "#00E5FFAB",
    "inputValidation.errorBackground": "#FF52521A",
    "inputValidation.errorBorder": "#FF5252",
    "inputValidation.warningBackground": "#FFB3001A",
    "inputValidation.warningBorder": "#FFB300",
    "inputValidation.infoBackground": "#00E5FF1A",
    "inputValidation.infoBorder": "#00E5FF",
    "dropdown.background": "#0A0A0A",
    "dropdown.border": "#1F1F1F",
    "dropdown.foreground": "#E0E0E0",
    "button.background": "#00E5FF",
    "button.foreground": "#000000",
    "button.hoverBackground": "#40EAFF",
    "button.secondaryBackground": "#0A0A0A",
    "button.secondaryForeground": "#E0E0E0",
    "checkbox.background": "#0A0A0A",
    "checkbox.foreground": "#B0B0B0",
    "checkbox.border": "#1F1F1F",
    "badge.background": "#00E5FF",
    "badge.foreground": "#000000",
    "progressBar.background": "#00E5FF",
    "peekView.border": "#1F1F1F",
    "peekViewEditor.background": "#141414",
    "peekViewEditor.matchHighlightBackground": "#FFB30021",
    "peekViewEditor.matchHighlightBorder": "#FFB30087",
    "peekViewResult.background": "#0A0A0A",
    "peekViewResult.matchHighlightBackground": "#141414",
    "peekViewTitle.background": "#0A0A0A",
    "peekViewTitleLabel.foreground": "#E0E0E0",
    "peekViewTitleDescription.foreground": "#707070",
    "quickInput.background": "#000000F8",
    "quickInput.foreground": "#E0E0E0",
    "quickInputTitle.background": "#141414",
    "pickerGroup.foreground": "#00E5FF",
    "pickerGroup.border": "#1F1F1F",
    "notifications.background": "#141414",
    "notifications.foreground": "#E0E0E0",
    "notifications.border": "#1F1F1F",
    "notificationCenter.border": "#1F1F1F",
    "notificationCenterHeader.background": "#0A0A0A",
    "notificationCenterHeader.foreground": "#E0E0E0",
    "notificationsErrorIcon.foreground": "#FF5252",
    "notificationsWarningIcon.foreground": "#FFB300",
    "notificationsInfoIcon.foreground": "#00E5FF",
    "breadcrumb.background": "#000000",
    "breadcrumb.foreground": "#707070",
    "breadcrumb.focusForeground": "#E0E0E0",
    "breadcrumb.activeSelectionForeground": "#00E5FF",
    "breadcrumbPicker.background": "#141414",
    "menu.background": "#141414",
    "menu.foreground": "#E0E0E0",
    "menu.separatorBackground": "#1F1F1F",
    "menu.selectionBackground": "#0A0A0A",
    "menu.selectionForeground": "#E0E0E0",
    "menu.selectionBorder": "#1F1F1F",
    "terminal.background": "#000000",
    "terminal.foreground": "#E0E0E0",
    "terminalCursor.foreground": "#00E5FF",
    "terminal.ansiBlack": "#000000",
    "terminal.ansiRed": "#FF5252",
    "terminal.ansiGreen": "#00E676",
    "terminal.ansiYellow": "#FFB300",
    "terminal.ansiBlue": "#00E5FF",
    "terminal.ansiMagenta": "#FF5252",
    "terminal.ansiCyan": "#00E5FF",
    "terminal.ansiWhite": "#B0B0B0",
    "terminal.ansiBrightBlack": "#707070",
    "terminal.ansiBrightRed": "#FF5252CC",
    "terminal.ansiBrightGreen": "#00E676CC",
    "terminal.ansiBrightYellow": "#FFB300CC",
    "terminal.ansiBrightBlue": "#00E5FFCC",
    "terminal.ansiBrightMagenta": "#FF5252CC",
    "terminal.ansiBrightCyan": "#40EAFF",
    "terminal.ansiBrightWhite": "#E0E0E0",
    "scrollbar.shadow": "#00000099",
    "scrollbarSlider.background": "#141414",
    "scrollbarSlider.hoverBackground": "#141414FF",
    "scrollbarSlider.activeBackground": "#141414FF",
    "focusBorder": "#00E5FF99",
    "selection.background": "#00E5FF33",
    "widget.shadow": "#00000099",
    "sash.hoverBorder": "#00E5FF",
    "editorInfo.foreground": "#00E5FF",
    "editorWarning.foreground": "#FFB300",
    "editorError.foreground": "#FF5252",
    "problemsErrorIcon.foreground": "#FF5252",
    "problemsWarningIcon.foreground": "#FFB300",
    "problemsInfoIcon.foreground": "#00E5FF",
    "testing.iconFailed": "#FF5252",
    "testing.iconErrored": "#FF5252CC",
    "testing.iconPassed": "#00E676",
    "testing.iconQueued": "#FFB300",
    "testing.iconSkipped": "#707070",
    "testing.peekBorder": "#1F1F1F",
    "debugToolBar.background": "#000000",
    "debugIcon.breakpointForeground": "#FF5252",
    "editor.stackFrameHighlightBackground": "#FFB3001A",
    "editor.focusedStackFrameHighlightBackground": "#00E6761A",
    "gitDecoration.addedResourceForeground": "#00E676",
    "gitDecoration.modifiedResourceForeground": "#FFB300",
    "gitDecoration.deletedResourceForeground": "#FF5252",
    "gitDecoration.renamedResourceForeground": "#00E5FF",
    "gitDecoration.untrackedResourceForeground": "#00E676CC",
    "gitDecoration.ignoredResourceForeground": "#707070",
    "gitDecoration.conflictingResourceForeground": "#FF5252CC",
    "gitDecoration.submoduleResourceForeground": "#FFB300CC",
    "editorLink.activeForeground": "#40EAFF",
    "textLink.foreground": "#40EAFF",
    "textLink.activeForeground": "#00E5FF",
    "textPreformat.foreground": "#B0B0B0",
    "textBlockQuote.background": "#000000",
    "textBlockQuote.border": "#1F1F1F",
    "textCodeBlock.background": "#0A0A0A",
    "textSeparator.foreground": "#1F1F1F",
    "editorUnnecessaryCode.opacity": "#E0E0E040",
    "listFilterWidget.background": "#0A0A0A",
    "listFilterWidget.outline": "#00E5FFAB",
    "listFilterWidget.noMatchesOutline": "#FF5252AB",
    "editorStickyScroll.background": "#000000F2",
    "editorStickyScrollHover.background": "#000000"
  },
  "tokenColors": [
    {
      "scope": [
        "comment",
        "punctuation.definition.comment"
      ],
      "settings": {
        "foreground": "#707070",
        "fontStyle": "italic"
      }
    },
    {
      "scope": [
        "keyword"
      ],
      "settings": {
        "foreground": "#FF5252",
        "fontStyle": "bold"
      }
    },
    {
      "scope": [
        "entity.name.function"
      ],
      "settings": {
        "foreground": "#00E5FF"
      }
    },
    {
      "scope": [
        "variable",
        "meta.definition.variable"
      ],
      "settings": {
        "foreground": "#E0E0E0"
      }
    },
    {
      "scope": [
        "string"
      ],
      "settings": {
        "foreground": "#00E676"
      }
    },
    {
      "scope": [
        "constant.numeric"
      ],
      "settings": {
        "foreground": "#FFB300"
      }
    },
    {
      "scope": [
        "constant.language",
        "constant.character"
      ],
      "settings": {
        "foreground": "#00E5FF"
      }
    },
    {
      "scope": [
        "storage.type",
        "storage.modifier"
      ],
      "settings": {
        "foreground": "#FF5252"
      }
    },
    {
      "scope": [
        "entity.name.type",
        "support.type",
        "support.class"
      ],
      "settings": {
        "foreground": "#00E5FF"
      }
    },
    {
      "scope": [
        "punctuation",
        "meta.brace"
      ],
      "settings": {
        "foreground": "#B0B0B0"
      }
    },
    {
      "scope": [
        "invalid",
        "invalid.illegal"
      ],
      "settings": {
        "foreground": "#FF5252",
        "fontStyle": "underline"
      }
    },
    {
      "scope": [
        "markup.bold",
        "markup.bold.markdown"
      ],
      "settings": {
        "fontStyle": "bold",
        "foreground": "#E0E0E0"
      }
    },
    {
      "scope": [
        "markup.italic",
        "markup.italic.markdown"
      ],
      "settings": {
        "fontStyle": "italic",
        "foreground": "#E0E0E0"
      }
    },
    {
      "scope": [
        "markup.inline.raw",
        "markup.raw.inline",
        "markup.inline.code"
      ],
      "settings": {
        "foreground": "#E0E0E0"
      }
    },
    {
      "scope": [
        "markup.heading",
        "entity.name.section",
        "punctuation.definition.heading.markdown"
      ],
      "settings": {
        "fontStyle": "bold",
        "foreground": "#00E5FF"
      }
    },
    {
      "scope": [
        "heading.1.markdown",
        "markup.heading.setext.1.markdown"
      ],
      "settings": {
        "fontStyle": "bold"
      }
    },
    {
      "scope": [
        "heading.2.markdown",
        "markup.heading.setext.2.markdown"
      ],
      "settings": {
        "fontStyle": "bold"
      }
    },
    {
      "scope": [
        "heading.3.markdown"
      ],
      "settings": {
        "fontStyle": "bold"
      }
    },
    {
      "scope": [
        "heading.4.markdown"
      ],
      "settings": {
        "fontStyle": "bold"
      }
    },
    {
      "scope": [
        "heading.5.markdown"
      ],
      "settings": {
        "fontStyle": "bold"
      }
    },
    {
      "scope": [
        "heading.6.markdown"
      ],
      "settings": {
        "fontStyle": "bold"
      }
    },
    {
      "scope": [
        "entity.name.tag.html",
        "entity.name.tag.xml"
      ],
      "settings": {
        "foreground": "#F7B883",
        "fontStyle": "bold"
      }
    },
    {
      "scope": [
        "entity.name.tag.structure.any.html",
        "entity.name.tag.block.any.html"
      ],
      "settings": {
        "foreground": "#FFD166",
        "fontStyle": "bold"
      }
    },
    {
      "scope": [
        "entity.name.tag.inline.any.html"
      ],
      "settings": {
        "foreground": "#EADCB2"
      }
    },
    {
      "scope": [
        "entity.name.tag.script.html",
        "entity.name.tag.style.html"
      ],
      "settings": {
        "foreground": "#FF3CAC",
        "fontStyle": "bold"
      }
    },
    {
      "scope": [
        "entity.other.attribute-name.html",
        "entity.other.attribute-name.xml"
      ],
      "settings": {
        "foreground": "#EADCB2",
        "fontStyle": "italic"
      }
    },
    {
      "scope": [
        "entity.other.attribute-name.class.html",
        "entity.other.attribute-name.class.css"
      ],
      "settings": {
        "foreground": "#C8B0FF",
        "fontStyle": "italic bold"
      }
    },
    {
      "scope": [
        "entity.other.attribute-name.id.html",
        "entity.other.attribute-name.id.css"
      ],
      "settings": {
        "foreground": "#4CFFCA",
        "fontStyle": "italic bold"
      }
    },
    {
      "scope": [
        "entity.other.attribute-name.style.html"
      ],
      "settings": {
        "foreground": "#FF8BDA",
        "fontStyle": "italic"
      }
    },
    {
      "scope": [
        "entity.other.attribute-name.event.html"
      ],
      "settings": {
        "foreground": "#D8C8FF",
        "fontStyle": "italic"
      }
    },
    {
      "scope": [
        "string.quoted.double.html",
        "string.quoted.single.html"
      ],
      "settings": {
        "foreground": "#00F5A0"
      }
    },
    {
      "scope": [
        "meta.attribute-with-value.html string"
      ],
      "settings": {
        "foreground": "#98FF66"
      }
    },
    {
      "scope": [
        "punctuation.definition.tag.begin.html",
        "punctuation.definition.tag.end.html"
      ],
      "settings": {
        "foreground": "#A6AAB4"
      }
    },
    {
      "scope": [
        "punctuation.definition.tag.html",
        "punctuation.separator.key-value.html"
      ],
      "settings": {
        "foreground": "#8E93A6"
      }
    },
    {
      "scope": [
        "punctuation.definition.string.begin.html",
        "punctuation.definition.string.end.html"
      ],
      "settings": {
        "foreground": "#9AA0B4"
      }
    },
    {
      "scope": [
        "comment.block.html",
        "punctuation.definition.comment.html"
      ],
      "settings": {
        "foreground": "#8E93A6",
        "fontStyle": "italic"
      }
    },
    {
      "scope": [
        "constant.character.entity.html",
        "constant.character.entity.named.html"
      ],
      "settings": {
        "foreground": "#F2C97D",
        "fontStyle": "bold"
      }
    },
    {
      "scope": [
        "punctuation.definition.entity.html"
      ],
      "settings": {
        "foreground": "#FFD166"
      }
    },
    {
      "scope": [
        "meta.tag.sgml.doctype.html",
        "entity.name.tag.doctype.html"
      ],
      "settings": {
        "foreground": "#FF3CAC",
        "fontStyle": "bold"
      }
    },
    {
      "scope": [
        "keyword.doctype.xml"
      ],
      "settings": {
        "foreground": "#FF3CAC",
        "fontStyle": "bold"
      }
    },
    {
      "scope": [
        "source.css.embedded.html"
      ],
      "settings": {
        "foreground": "#E0CCFF"
      }
    },
    {
      "scope": [
        "meta.embedded.block.css"
      ],
      "settings": {
        "foreground": "#D7C7FF"
      }
    },
    {
      "scope": [
        "source.js.embedded.html",
        "source.javascript.embedded.html"
      ],
      "settings": {
        "foreground": "#F7B883"
      }
    },
    {
      "scope": [
        "meta.embedded.block.javascript"
      ],
      "settings": {
        "foreground": "#EADCB2"
      }
    },
    {
      "scope": [
        "entity.name.tag.form.html",
        "entity.name.tag.input.html",
        "entity.name.tag.button.html"
      ],
      "settings": {
        "foreground": "#79E49A",
        "fontStyle": "bold"
      }
    },
    {
      "scope": [
        "entity.other.attribute-name.form.html"
      ],
      "settings": {
        "foreground": "#98FF66",
        "fontStyle": "italic"
      }
    },
    {
      "scope": [
        "entity.name.tag.table.html",
        "entity.name.tag.tr.html",
        "entity.name.tag.td.html",
        "entity.name.tag.th.html"
      ],
      "settings": {
        "foreground": "#4CFFCA",
        "fontStyle": "bold"
      }
    },
    {
      "scope": [
        "entity.name.tag.img.html",
        "entity.name.tag.video.html",
        "entity.name.tag.audio.html"
      ],
      "settings": {
        "foreground": "#FFD166",
        "fontStyle": "bold"
      }
    },
    {
      "scope": [
        "entity.name.tag.a.html"
      ],
      "settings": {
        "foreground": "#4CFFCA",
        "fontStyle": "bold"
      }
    },
    {
      "scope": [
        "entity.other.attribute-name.href.html"
      ],
      "settings": {
        "foreground": "#00F5A0",
        "fontStyle": "italic bold"
      }
    },
    {
      "scope": [
        "entity.name.tag.header.html",
        "entity.name.tag.main.html",
        "entity.name.tag.footer.html",
        "entity.name.tag.nav.html",
        "entity.name.tag.aside.html",
        "entity.name.tag.section.html",
        "entity.name.tag.article.html",
        "entity.name.tag.figure.html",
        "entity.name.tag.figcaption.html"
      ],
      "settings": {
        "foreground": "#C8B0FF",
        "fontStyle": "bold"
      }
    },
    {
      "scope": [
        "text.html.basic"
      ],
      "settings": {
        "foreground": "#F7F8FA"
      }
    }
  ]
}