{
  "$schema": "vscode://schemas/color-theme",
  "name": "XELA Stone Garden — Natural Balance",
  "type": "light",
  "semanticHighlighting": true,
  "xGenerated": true,
  "colors": {
    "titleBar.activeBackground": "#ECE9E4",
    "titleBar.inactiveBackground": "#ECE9E4",
    "titleBar.activeForeground": "#2A2620",
    "titleBar.inactiveForeground": "#8A8178",
    "titleBar.border": "#D8D3CC",
    "window.activeBorder": "#7A6F5D",
    "window.inactiveBorder": "#D8D3CC",
    "activityBar.background": "#ECE9E4",
    "activityBar.foreground": "#2A2620",
    "activityBar.inactiveForeground": "#8A8178",
    "activityBar.border": "#D8D3CC",
    "activityBar.activeBorder": "#7A6F5D",
    "activityBarBadge.background": "#7A6F5D",
    "activityBarBadge.foreground": "#FFFFFF",
    "sideBar.background": "#ECE9E4",
    "sideBar.foreground": "#2A2620",
    "sideBar.border": "#E3DFD8",
    "sideBarTitle.foreground": "#5A534A",
    "sideBarSectionHeader.background": "#FAF8F5",
    "sideBar.dropBackground": "#7A6F5D21",
    "statusBar.background": "#FAF8F5",
    "statusBar.foreground": "#2A2620",
    "statusBar.border": "#D8D3CC",
    "statusBar.noFolderBackground": "#FAF8F5",
    "statusBar.noFolderForeground": "#5A534A",
    "statusBar.debuggingBackground": "#C4905E",
    "statusBar.debuggingForeground": "#FFFFFF",
    "statusBarItem.hoverBackground": "#FAF8F5",
    "statusBarItem.remoteBackground": "#5B8A8A",
    "statusBarItem.remoteForeground": "#FFFFFF",
    "statusBarItem.prominentBackground": "#FAF8F5",
    "statusBarItem.prominentHoverBackground": "#FFFFFF",
    "statusBarItem.errorBackground": "#C45E5E",
    "statusBarItem.errorForeground": "#FFFFFF",
    "statusBarItem.warningBackground": "#C4905E",
    "statusBarItem.warningForeground": "#FFFFFF",
    "panel.background": "#F0EDE8",
    "panel.border": "#E3DFD8",
    "panel.dropBorder": "#7A6F5D",
    "panelTitle.activeForeground": "#2A2620",
    "panelTitle.activeBorder": "#7A6F5D",
    "panelTitle.inactiveForeground": "#5A534A",
    "editorGroupHeader.tabsBackground": "#ECE9E4",
    "editorGroupHeader.tabsBorder": "#D8D3CC",
    "editorGroup.dropBackground": "#7A6F5D21",
    "tab.activeBackground": "#F5F3F0",
    "tab.inactiveBackground": "#ECE9E4",
    "tab.border": "#FAF8F5",
    "tab.activeForeground": "#2A2620",
    "tab.inactiveForeground": "#8A8178",
    "tab.activeBorderTop": "#7A6F5D",
    "tab.unfocusedActiveBorderTop": "#C4905E87",
    "tab.hoverBackground": "#FFFFFF",
    "tab.hoverForeground": "#2A2620",
    "tab.unfocusedHoverBackground": "#FFFFFF",
    "tab.activeModifiedBorder": "#C4905E",
    "tab.hoverBorder": "#FFFFFF",
    "tab.lastPinnedBorder": "#D8D3CC",
    "editor.background": "#F5F3F0",
    "editor.foreground": "#2A2620",
    "editor.lineHighlightBackground": "#ECE9E450",
    "editor.selectionBackground": "#7A6F5D29",
    "editor.inactiveSelectionBackground": "#7A6F5D99",
    "editor.selectionHighlightBackground": "#7A6F5D99",
    "editor.selectionHighlightBorder": "#7A6F5D54",
    "editor.wordHighlightBackground": "#7A6F5D1A",
    "editor.wordHighlightStrongBackground": "#7A6F5D2B",
    "editor.foldBackground": "#ECE9E480",
    "editor.findMatchBackground": "#00000000",
    "editor.findMatchBorder": "#C4905E",
    "editor.findMatchHighlightBackground": "#FAF8F580",
    "editor.findMatchHighlightBorder": "#C4905E87",
    "editor.hoverHighlightBackground": "#FAF8F580",
    "editorCursor.foreground": "#7A6F5D",
    "editorLineNumber.foreground": "#AEA89F",
    "editorLineNumber.activeForeground": "#5A534A",
    "editorHoverWidget.background": "#FFFFFF",
    "editorHoverWidget.border": "#D8D3CC",
    "editorWidget.background": "#FFFFFF",
    "editorWidget.border": "#D8D3CC",
    "editorWidget.resizeBorder": "#7A6F5D",
    "editorIndentGuide.background1": "#FAF8F5",
    "editorIndentGuide.activeBackground1": "#8A8178B3",
    "editorBracketMatch.background": "#FAF8F5",
    "editorBracketMatch.border": "#C4905E87",
    "editorBracketHighlight.foreground1": "#7A6F5D",
    "editorBracketHighlight.foreground2": "#C4905E",
    "editorBracketHighlight.foreground3": "#C45E5E",
    "editorBracketHighlight.foreground4": "#5B8A8A",
    "editorBracketHighlight.foreground5": "#6B8A5B",
    "editorBracketHighlight.foreground6": "#8F836F",
    "editorBracketPairGuide.activeBackground1": "#7A6F5D54",
    "editorBracketPairGuide.activeBackground2": "#C4905E54",
    "editorBracketPairGuide.activeBackground3": "#C45E5E54",
    "editorBracketPairGuide.activeBackground4": "#5B8A8A54",
    "editorBracketPairGuide.activeBackground5": "#6B8A5B54",
    "editorBracketPairGuide.activeBackground6": "#8F836F54",
    "diffEditor.insertedTextBackground": "#6B8A5B21",
    "diffEditor.removedTextBackground": "#C45E5E21",
    "diffEditor.insertedLineBackground": "#6B8A5B1A",
    "diffEditor.removedLineBackground": "#C45E5E1A",
    "editorOverviewRuler.errorForeground": "#C45E5EAB",
    "editorOverviewRuler.warningForeground": "#C4905EAB",
    "editorOverviewRuler.infoForeground": "#5B8A8A87",
    "editorOverviewRuler.findMatchForeground": "#C4905E87",
    "editorOverviewRuler.modifiedForeground": "#C4905E66",
    "editorOverviewRuler.addedForeground": "#6B8A5B66",
    "editorOverviewRuler.deletedForeground": "#C45E5E66",
    "editorGutter.addedBackground": "#6B8A5BAB",
    "editorGutter.modifiedBackground": "#C4905EAB",
    "editorGutter.deletedBackground": "#C45E5EAB",
    "editorGutter.commentRangeForeground": "#8A8178",
    "minimap.findMatchHighlight": "#C4905E99",
    "minimap.selectionHighlight": "#7A6F5D54",
    "minimap.selectionOccurrenceHighlight": "#7A6F5D33",
    "minimap.errorHighlight": "#C45E5E99",
    "minimap.warningHighlight": "#C4905E99",
    "list.activeSelectionBackground": "#E3DFD8",
    "list.activeSelectionForeground": "#2A2620",
    "list.inactiveSelectionBackground": "#ECE9E4",
    "list.hoverBackground": "#F0EDE8",
    "list.focusBackground": "#ECE9E4",
    "list.highlightForeground": "#7A6F5D",
    "list.warningForeground": "#C4905E",
    "list.errorForeground": "#C45E5E",
    "list.dropBackground": "#7A6F5D21",
    "input.background": "#FAF8F5",
    "input.foreground": "#2A2620",
    "input.border": "#D8D3CC",
    "input.placeholderForeground": "#8A8178",
    "inputOption.activeBorder": "#7A6F5DAB",
    "inputValidation.errorBackground": "#C45E5E1A",
    "inputValidation.errorBorder": "#C45E5E",
    "inputValidation.warningBackground": "#C4905E1A",
    "inputValidation.warningBorder": "#C4905E",
    "inputValidation.infoBackground": "#5B8A8A1A",
    "inputValidation.infoBorder": "#5B8A8A",
    "dropdown.background": "#FAF8F5",
    "dropdown.border": "#D8D3CC",
    "dropdown.foreground": "#2A2620",
    "button.background": "#7A6F5D",
    "button.foreground": "#FFFFFF",
    "button.hoverBackground": "#8F836F",
    "checkbox.background": "#FAF8F5",
    "checkbox.foreground": "#5A534A",
    "checkbox.border": "#D8D3CC",
    "badge.background": "#7A6F5D",
    "badge.foreground": "#FFFFFF",
    "progressBar.background": "#7A6F5D",
    "peekView.border": "#D8D3CC",
    "peekViewEditor.background": "#FFFFFF",
    "peekViewEditor.matchHighlightBackground": "#C4905E21",
    "peekViewEditor.matchHighlightBorder": "#C4905E87",
    "peekViewResult.background": "#FAF8F5",
    "peekViewResult.matchHighlightBackground": "#FFFFFF",
    "peekViewTitle.background": "#FAF8F5",
    "peekViewTitleLabel.foreground": "#2A2620",
    "peekViewTitleDescription.foreground": "#8A8178",
    "quickInput.background": "#F5F3F0F5",
    "quickInput.foreground": "#2A2620",
    "quickInputTitle.background": "#FFFFFF",
    "pickerGroup.foreground": "#7A6F5D",
    "pickerGroup.border": "#D8D3CC",
    "notifications.background": "#FFFFFF",
    "notifications.border": "#D8D3CC",
    "notificationCenterHeader.foreground": "#2A2620",
    "breadcrumb.background": "#F5F3F0",
    "breadcrumb.foreground": "#8A8178",
    "breadcrumb.focusForeground": "#2A2620",
    "breadcrumb.activeSelectionForeground": "#7A6F5D",
    "breadcrumbPicker.background": "#FFFFFF",
    "menu.background": "#FFFFFF",
    "menu.foreground": "#2A2620",
    "menu.separatorBackground": "#D8D3CC",
    "menu.selectionBackground": "#FAF8F5",
    "menu.selectionForeground": "#2A2620",
    "menu.selectionBorder": "#D8D3CC",
    "terminal.background": "#F5F3F0",
    "terminal.foreground": "#2A2620",
    "terminalCursor.foreground": "#7A6F5D",
    "terminal.ansiBlack": "#F5F3F0",
    "terminal.ansiRed": "#C45E5E",
    "terminal.ansiGreen": "#6B8A5B",
    "terminal.ansiYellow": "#C4905E",
    "terminal.ansiBlue": "#5B8A8A",
    "terminal.ansiMagenta": "#C45E5E",
    "terminal.ansiCyan": "#7A6F5D",
    "terminal.ansiWhite": "#5A534A",
    "terminal.ansiBrightBlack": "#8A8178",
    "terminal.ansiBrightRed": "#C45E5ECC",
    "terminal.ansiBrightGreen": "#6B8A5BCC",
    "terminal.ansiBrightYellow": "#C4905ECC",
    "terminal.ansiBrightBlue": "#5B8A8ACC",
    "terminal.ansiBrightMagenta": "#C45E5ECC",
    "terminal.ansiBrightCyan": "#8F836F",
    "terminal.ansiBrightWhite": "#2A2620",
    "scrollbar.shadow": "#00000015",
    "scrollbarSlider.background": "#FFFFFF",
    "scrollbarSlider.hoverBackground": "#FFFFFFFF",
    "scrollbarSlider.activeBackground": "#FFFFFFFF",
    "focusBorder": "#7A6F5D80",
    "selection.background": "#7A6F5D29",
    "widget.shadow": "#00000015",
    "sash.hoverBorder": "#7A6F5D",
    "editorInfo.foreground": "#5B8A8A",
    "editorWarning.foreground": "#C4905E",
    "editorError.foreground": "#C45E5E",
    "problemsErrorIcon.foreground": "#C45E5E",
    "problemsWarningIcon.foreground": "#C4905E",
    "problemsInfoIcon.foreground": "#5B8A8A",
    "testing.iconFailed": "#C45E5E",
    "testing.iconErrored": "#C45E5ECC",
    "testing.iconPassed": "#6B8A5B",
    "testing.iconQueued": "#C4905E",
    "testing.iconSkipped": "#8A8178",
    "testing.peekBorder": "#D8D3CC",
    "debugToolBar.background": "#ECE9E4",
    "debugIcon.breakpointForeground": "#C45E5E",
    "editor.stackFrameHighlightBackground": "#C4905E1A",
    "editor.focusedStackFrameHighlightBackground": "#6B8A5B1A",
    "gitDecoration.addedResourceForeground": "#6B8A5B",
    "gitDecoration.modifiedResourceForeground": "#C4905E",
    "gitDecoration.deletedResourceForeground": "#C45E5E",
    "gitDecoration.renamedResourceForeground": "#5B8A8A",
    "gitDecoration.untrackedResourceForeground": "#6B8A5BCC",
    "gitDecoration.ignoredResourceForeground": "#8A8178",
    "gitDecoration.conflictingResourceForeground": "#C45E5ECC",
    "gitDecoration.submoduleResourceForeground": "#C4905ECC",
    "editorLink.activeForeground": "#5B8A8A",
    "textLink.foreground": "#5B8A8A",
    "textLink.activeForeground": "#7A6F5D",
    "textPreformat.foreground": "#5A534A",
    "textBlockQuote.background": "#ECE9E4",
    "textBlockQuote.border": "#D8D3CC",
    "textCodeBlock.background": "#FAF8F5",
    "textSeparator.foreground": "#D8D3CC",
    "editorUnnecessaryCode.opacity": "#2A262040",
    "listFilterWidget.background": "#FAF8F5",
    "listFilterWidget.outline": "#7A6F5DAB",
    "listFilterWidget.noMatchesOutline": "#C45E5EAB",
    "editorStickyScroll.background": "#F5F3F0F2",
    "editorStickyScrollHover.background": "#ECE9E4",
    "tab.activeBorder": "#7A6F5D",
    "editorGroup.border": "#E3DFD8",
    "editorIndentGuide.background": "#D8D3CC25",
    "editorIndentGuide.activeBackground": "#D8D3CC70"
  },
  "tokenColors": [
    {
      "scope": [
        "comment",
        "punctuation.definition.comment"
      ],
      "settings": {
        "foreground": "#8A8178",
        "fontStyle": "italic"
      }
    },
    {
      "scope": [
        "keyword"
      ],
      "settings": {
        "foreground": "#C45E5E",
        "fontStyle": "bold"
      }
    },
    {
      "scope": [
        "entity.name.function"
      ],
      "settings": {
        "foreground": "#5B8A8A"
      }
    },
    {
      "scope": [
        "variable",
        "meta.definition.variable"
      ],
      "settings": {
        "foreground": "#2A2620"
      }
    },
    {
      "scope": [
        "string"
      ],
      "settings": {
        "foreground": "#6B8A5B"
      }
    },
    {
      "scope": [
        "constant.numeric"
      ],
      "settings": {
        "foreground": "#C4905E"
      }
    },
    {
      "scope": [
        "constant.language",
        "constant.character"
      ],
      "settings": {
        "foreground": "#7A6F5D"
      }
    },
    {
      "scope": [
        "storage.type",
        "storage.modifier"
      ],
      "settings": {
        "foreground": "#C45E5E"
      }
    },
    {
      "scope": [
        "entity.name.type",
        "support.type",
        "support.class"
      ],
      "settings": {
        "foreground": "#5B8A8A"
      }
    },
    {
      "scope": [
        "punctuation",
        "meta.brace"
      ],
      "settings": {
        "foreground": "#5A534A"
      }
    },
    {
      "scope": [
        "invalid",
        "invalid.illegal"
      ],
      "settings": {
        "foreground": "#C45E5E",
        "fontStyle": "underline"
      }
    },
    {
      "scope": [
        "markup.bold",
        "markup.bold.markdown"
      ],
      "settings": {
        "fontStyle": "bold",
        "foreground": "#2A2620"
      }
    },
    {
      "scope": [
        "markup.italic",
        "markup.italic.markdown"
      ],
      "settings": {
        "fontStyle": "italic",
        "foreground": "#2A2620"
      }
    },
    {
      "scope": [
        "markup.inline.raw",
        "markup.raw.inline",
        "markup.inline.code"
      ],
      "settings": {
        "foreground": "#2A2620"
      }
    },
    {
      "scope": [
        "markup.heading",
        "entity.name.section",
        "punctuation.definition.heading.markdown"
      ],
      "settings": {
        "fontStyle": "bold",
        "foreground": "#7A6F5D"
      }
    },
    {
      "scope": [
        "heading.1.markdown",
        "markup.heading.setext.1.markdown"
      ],
      "settings": {
        "fontStyle": "bold",
        "foreground": "#5B8A8A"
      }
    },
    {
      "scope": [
        "heading.2.markdown",
        "markup.heading.setext.2.markdown"
      ],
      "settings": {
        "fontStyle": "bold",
        "foreground": "#6B8A5B"
      }
    },
    {
      "scope": [
        "heading.3.markdown"
      ],
      "settings": {
        "fontStyle": "bold",
        "foreground": "#C4905E"
      }
    },
    {
      "scope": [
        "heading.4.markdown"
      ],
      "settings": {
        "fontStyle": "bold",
        "foreground": "#7A6F5D"
      }
    },
    {
      "scope": [
        "heading.5.markdown"
      ],
      "settings": {
        "fontStyle": "bold",
        "foreground": "#5A534A"
      }
    },
    {
      "scope": [
        "heading.6.markdown"
      ],
      "settings": {
        "fontStyle": "bold",
        "foreground": "#8A8178"
      }
    },
    {
      "scope": [
        "entity.name.tag.html",
        "entity.name.tag.xml"
      ],
      "settings": {
        "foreground": "#F7B883",
        "fontStyle": "bold"
      }
    },
    {
      "scope": [
        "entity.name.tag.structure.any.html",
        "entity.name.tag.block.any.html"
      ],
      "settings": {
        "foreground": "#FFD166",
        "fontStyle": "bold"
      }
    },
    {
      "scope": [
        "entity.name.tag.inline.any.html"
      ],
      "settings": {
        "foreground": "#EADCB2"
      }
    },
    {
      "scope": [
        "entity.name.tag.script.html",
        "entity.name.tag.style.html"
      ],
      "settings": {
        "foreground": "#FF3CAC",
        "fontStyle": "bold"
      }
    },
    {
      "scope": [
        "entity.other.attribute-name.html",
        "entity.other.attribute-name.xml"
      ],
      "settings": {
        "foreground": "#EADCB2",
        "fontStyle": "italic"
      }
    },
    {
      "scope": [
        "entity.other.attribute-name.class.html",
        "entity.other.attribute-name.class.css"
      ],
      "settings": {
        "foreground": "#C8B0FF",
        "fontStyle": "italic bold"
      }
    },
    {
      "scope": [
        "entity.other.attribute-name.id.html",
        "entity.other.attribute-name.id.css"
      ],
      "settings": {
        "foreground": "#4CFFCA",
        "fontStyle": "italic bold"
      }
    },
    {
      "scope": [
        "entity.other.attribute-name.style.html"
      ],
      "settings": {
        "foreground": "#FF8BDA",
        "fontStyle": "italic"
      }
    },
    {
      "scope": [
        "entity.other.attribute-name.event.html"
      ],
      "settings": {
        "foreground": "#D8C8FF",
        "fontStyle": "italic"
      }
    },
    {
      "scope": [
        "string.quoted.double.html",
        "string.quoted.single.html"
      ],
      "settings": {
        "foreground": "#00F5A0"
      }
    },
    {
      "scope": [
        "meta.attribute-with-value.html string"
      ],
      "settings": {
        "foreground": "#98FF66"
      }
    },
    {
      "scope": [
        "punctuation.definition.tag.begin.html",
        "punctuation.definition.tag.end.html"
      ],
      "settings": {
        "foreground": "#A6AAB4"
      }
    },
    {
      "scope": [
        "punctuation.definition.tag.html",
        "punctuation.separator.key-value.html"
      ],
      "settings": {
        "foreground": "#8E93A6"
      }
    },
    {
      "scope": [
        "punctuation.definition.string.begin.html",
        "punctuation.definition.string.end.html"
      ],
      "settings": {
        "foreground": "#9AA0B4"
      }
    },
    {
      "scope": [
        "comment.block.html",
        "punctuation.definition.comment.html"
      ],
      "settings": {
        "foreground": "#8E93A6",
        "fontStyle": "italic"
      }
    },
    {
      "scope": [
        "constant.character.entity.html",
        "constant.character.entity.named.html"
      ],
      "settings": {
        "foreground": "#F2C97D",
        "fontStyle": "bold"
      }
    },
    {
      "scope": [
        "punctuation.definition.entity.html"
      ],
      "settings": {
        "foreground": "#FFD166"
      }
    },
    {
      "scope": [
        "meta.tag.sgml.doctype.html",
        "entity.name.tag.doctype.html"
      ],
      "settings": {
        "foreground": "#FF3CAC",
        "fontStyle": "bold"
      }
    },
    {
      "scope": [
        "keyword.doctype.xml"
      ],
      "settings": {
        "foreground": "#FF3CAC",
        "fontStyle": "bold"
      }
    },
    {
      "scope": [
        "source.css.embedded.html"
      ],
      "settings": {
        "foreground": "#E0CCFF"
      }
    },
    {
      "scope": [
        "meta.embedded.block.css"
      ],
      "settings": {
        "foreground": "#D7C7FF"
      }
    },
    {
      "scope": [
        "source.js.embedded.html",
        "source.javascript.embedded.html"
      ],
      "settings": {
        "foreground": "#F7B883"
      }
    },
    {
      "scope": [
        "meta.embedded.block.javascript"
      ],
      "settings": {
        "foreground": "#EADCB2"
      }
    },
    {
      "scope": [
        "entity.name.tag.form.html",
        "entity.name.tag.input.html",
        "entity.name.tag.button.html"
      ],
      "settings": {
        "foreground": "#79E49A",
        "fontStyle": "bold"
      }
    },
    {
      "scope": [
        "entity.other.attribute-name.form.html"
      ],
      "settings": {
        "foreground": "#98FF66",
        "fontStyle": "italic"
      }
    },
    {
      "scope": [
        "entity.name.tag.table.html",
        "entity.name.tag.tr.html",
        "entity.name.tag.td.html",
        "entity.name.tag.th.html"
      ],
      "settings": {
        "foreground": "#4CFFCA",
        "fontStyle": "bold"
      }
    },
    {
      "scope": [
        "entity.name.tag.img.html",
        "entity.name.tag.video.html",
        "entity.name.tag.audio.html"
      ],
      "settings": {
        "foreground": "#FFD166",
        "fontStyle": "bold"
      }
    },
    {
      "scope": [
        "entity.name.tag.a.html"
      ],
      "settings": {
        "foreground": "#4CFFCA",
        "fontStyle": "bold"
      }
    },
    {
      "scope": [
        "entity.other.attribute-name.href.html"
      ],
      "settings": {
        "foreground": "#00F5A0",
        "fontStyle": "italic bold"
      }
    },
    {
      "scope": [
        "entity.name.tag.header.html",
        "entity.name.tag.main.html",
        "entity.name.tag.footer.html",
        "entity.name.tag.nav.html",
        "entity.name.tag.aside.html",
        "entity.name.tag.section.html",
        "entity.name.tag.article.html",
        "entity.name.tag.figure.html",
        "entity.name.tag.figcaption.html"
      ],
      "settings": {
        "foreground": "#C8B0FF",
        "fontStyle": "bold"
      }
    },
    {
      "scope": [
        "text.html.basic"
      ],
      "settings": {
        "foreground": "#F7F8FA"
      }
    }
  ],
  "semanticTokenColors": {
    "function": "#00F5A0",
    "string": "#22C55E",
    "number": "#FFD166",
    "keyword": "#FFD166",
    "type": "#D8C8FF"
  }
}